[
	{
		"id": 147835,
		"name": "Maki Salces",
		"name_second": "Maki Salces"
	},
	{
		"id": 269694,
		"name": "Oseas Mendieta",
		"name_second": "Oseas Mendieta"
	},
	{
		"id": 210436,
		"name": "Mario Barbery",
		"name_second": "Mario Barbery"
	},
	{
		"id": 95346,
		"name": "Darwin Rios Pinto",
		"name_second": "Darwin Rios Pinto"
	},
	{
		"id": 91885,
		"name": "Jose Gabriel Rios",
		"name_second": "Jose Gabriel Rios"
	},
	{
		"id": 222351,
		"name": "Henrry Torrez",
		"name_second": "Henrry Torrez"
	},
	{
		"id": 232896,
		"name": "Francescoly Bejarano",
		"name_second": "Francescoly Bejarano"
	},
	{
		"id": 269692,
		"name": "Rolin Ribera",
		"name_second": "Rolin Ribera"
	},
	{
		"id": 232898,
		"name": "Miguel Mendoza",
		"name_second": "Miguel Mendoza"
	},
	{
		"id": 233637,
		"name": "Carlos Dellien",
		"name_second": "Carlos Dellien"
	},
	{
		"id": 232902,
		"name": "Alejandro Anez",
		"name_second": "Alejandro Anez"
	},
	{
		"id": 233638,
		"name": "Juan Justiniano",
		"name_second": "Juan Justiniano"
	},
	{
		"id": 232888,
		"name": "Marcelo Villagomez",
		"name_second": "Marcelo Villagomez"
	},
	{
		"id": 269696,
		"name": "James Kremser",
		"name_second": "James Kremser"
	},
	{
		"id": 232890,
		"name": "Amir Bejarano",
		"name_second": "Amir Bejarano"
	},
	{
		"id": 222337,
		"name": "Rodrigo Orihuela",
		"name_second": "Rodrigo Orihuela"
	},
	{
		"id": 69219,
		"name": "Mauro Ramiro Milano",
		"name_second": "Mauro Ramiro Milano"
	},
	{
		"id": 232889,
		"name": "Frank Oni",
		"name_second": "Frank Oni"
	},
	{
		"id": 187431,
		"name": "Clovis Daniel Roca Ugarteche",
		"name_second": "Clovis Daniel Roca Ugarteche"
	},
	{
		"id": 146009,
		"name": "Juan Pablo Aleman",
		"name_second": "Juan Pablo Aleman"
	},
	{
		"id": 124870,
		"name": "Ronny Rodriguez Pena",
		"name_second": "Ronny Rodriguez Pena"
	},
	{
		"id": 231673,
		"name": "Juan Pablo Gomez",
		"name_second": "Juan Pablo Gomez"
	},
	{
		"id": 232891,
		"name": "Denilso Fernandez",
		"name_second": "Denilso Fernandez"
	},
	{
		"id": 269693,
		"name": "Fabian Roman",
		"name_second": "Fabian Roman"
	},
	{
		"id": 232510,
		"name": "Grovert Carrillo",
		"name_second": "Grovert Carrillo"
	},
	{
		"id": 246169,
		"name": "Pedro Tomicha",
		"name_second": "Pedro Tomicha"
	},
	{
		"id": 233639,
		"name": "Jose Arriaga",
		"name_second": "Jose Arriaga"
	},
	{
		"id": 210456,
		"name": "Jorge Vargas",
		"name_second": "Jorge Vargas"
	},
	{
		"id": 232893,
		"name": "Gil Sergio",
		"name_second": "Gil Sergio"
	},
	{
		"id": 269695,
		"name": "Daniel Aguilera",
		"name_second": "Daniel Aguilera"
	},
	{
		"id": 131840,
		"name": "Juan Carlos Robles",
		"name_second": "Juan Carlos Robles"
	},
	{
		"id": 213915,
		"name": "Rodrigo Paniagua",
		"name_second": "Rodrigo Paniagua"
	},
	{
		"id": 149613,
		"name": "Marco Vaca",
		"name_second": "Marco Vaca"
	},
	{
		"id": 187458,
		"name": "Daniel Sandy",
		"name_second": "Daniel Sandy"
	}
]