[
	{
		"id": 181669,
		"name": "Mubarak Al Faneni",
		"name_second": "Mubarak Al Faneni"
	},
	{
		"id": 242793,
		"name": "Mohammad Daham",
		"name_second": "Mohammad Daham"
	},
	{
		"id": 128809,
		"name": "Faisal Zayed Alharbi",
		"name_second": "Faisal Zayed Alharbi"
	},
	{
		"id": 226693,
		"name": "Ali Khalaf",
		"name_second": "Ali Khalaf"
	},
	{
		"id": 245048,
		"name": "Athbi Shehab",
		"name_second": "Athbi Shehab"
	},
	{
		"id": 173605,
		"name": "Ahmad Al Dhefiri",
		"name_second": "Ahmad Al Dhefiri"
	},
	{
		"id": 181673,
		"name": "Eid Naser Al Rashedi",
		"name_second": "Eid Naser Al Rashedi"
	},
	{
		"id": 220117,
		"name": "Mohammad Redha",
		"name_second": "Mohammad Redha"
	},
	{
		"id": 220113,
		"name": "Bandar Bourslee",
		"name_second": "Bandar Bourslee"
	},
	{
		"id": 245056,
		"name": "Bader Tareq Ali",
		"name_second": "Bader Tareq Ali"
	},
	{
		"id": 262719,
		"name": "Salman Bormeya",
		"name_second": "Salman Bormeya"
	},
	{
		"id": 182899,
		"name": "Meshari Ghanam",
		"name_second": "Meshari Ghanam"
	},
	{
		"id": 16848,
		"name": "Hamad Al Anezi",
		"name_second": "Hamad Al Anezi"
	},
	{
		"id": 128811,
		"name": "Khaled Ebrahim Hajiah",
		"name_second": "Khaled Ebrahim Hajiah"
	},
	{
		"id": 128806,
		"name": "Fahad Alhajeri",
		"name_second": "Fahad Alhajeri"
	},
	{
		"id": 245044,
		"name": "Hamad Al-Harbi",
		"name_second": "Hamad Al-Harbi"
	},
	{
		"id": 182692,
		"name": "Sami Al Sanea",
		"name_second": "Sami Al Sanea"
	},
	{
		"id": 128880,
		"name": "Sulaiman Abdulghafoor",
		"name_second": "Sulaiman Abdulghafoor"
	},
	{
		"id": 280809,
		"name": "Abdulrahman Al-Fadhli",
		"name_second": "Abdulrahman Al-Fadhli"
	}
]