[
	{
		"id": 230003,
		"name": "Adel Mahamoud",
		"name_second": "Adel Mahamoud"
	},
	{
		"id": 234477,
		"name": "Stredair Appuah",
		"name_second": "Stredair Appuah"
	},
	{
		"id": 122035,
		"name": "Moses Simon",
		"name_second": "Moses Simon"
	},
	{
		"id": 157702,
		"name": "Ignatius Kpene Ganago",
		"name_second": "Ignatius Kpene Ganago"
	},
	{
		"id": 137888,
		"name": "Tino Kadewere",
		"name_second": "Tino Kadewere"
	},
	{
		"id": 182712,
		"name": "Mostafa Mohamed",
		"name_second": "Mostafa Mohamed Ahmed Abdalla"
	},
	{
		"id": 209933,
		"name": "Matthis Abline",
		"name_second": "Matthis Abline"
	},
	{
		"id": 228069,
		"name": "Joe-Loic Affamah",
		"name_second": "Joe-Loic Affamah"
	},
	{
		"id": 206132,
		"name": "Benie Adama Traore",
		"name_second": "Benie Adama Traore"
	},
	{
		"id": 128930,
		"name": "Marcus Regis Coco",
		"name_second": "Marcus Regis Coco"
	},
	{
		"id": 178432,
		"name": "Abdoul Kader Bamba",
		"name_second": "Abdoul Kader Bamba"
	},
	{
		"id": 275791,
		"name": "Mathis Oger",
		"name_second": "Mathis Oger"
	},
	{
		"id": 135848,
		"name": "Douglas Augusto Gomes Soares",
		"name_second": "Douglas Augusto Gomes Soares"
	},
	{
		"id": 156109,
		"name": "Samuel Moutoussamy",
		"name_second": "Samuel Moutoussamy"
	},
	{
		"id": 24905,
		"name": "Moussa Sissoko",
		"name_second": "Moussa Sissoko"
	},
	{
		"id": 221472,
		"name": "Mohamed Achi",
		"name_second": "Mohamed Achi"
	},
	{
		"id": 100026,
		"name": "Florent Mollet",
		"name_second": "Florent Mollet"
	},
	{
		"id": 138073,
		"name": "Pedro Chirivella",
		"name_second": "Pedro Chirivella"
	},
	{
		"id": 256024,
		"name": "Hugo Boutsingkham",
		"name_second": "Hugo Boutsingkham"
	},
	{
		"id": 145418,
		"name": "Jean Kevin Duverne",
		"name_second": "Jean Kevin Duverne"
	},
	{
		"id": 78164,
		"name": "Nicolas Pallois",
		"name_second": "Nicolas Pallois"
	},
	{
		"id": 120661,
		"name": "Jean-Charles Castelletto",
		"name_second": "Jean-Charles Castelletto"
	},
	{
		"id": 217153,
		"name": "Yannis MBemba",
		"name_second": "Yannis MBemba"
	},
	{
		"id": 143796,
		"name": "Eray Ervin Comert",
		"name_second": "Eray Ervin Comert"
	},
	{
		"id": 231710,
		"name": "Nathan Zeze",
		"name_second": "Nathan Zeze"
	},
	{
		"id": 154958,
		"name": "Nicolas Cozza",
		"name_second": "Nicolas Cozza"
	},
	{
		"id": 138475,
		"name": "Kelvin Amian Adou",
		"name_second": "Kelvin Amian Adou"
	},
	{
		"id": 139372,
		"name": "Alban Lafont",
		"name_second": "Alban Lafont"
	},
	{
		"id": 145205,
		"name": "Remy Descamps",
		"name_second": "Remy Descamps"
	},
	{
		"id": 26869,
		"name": "Denis Petric",
		"name_second": "Denis Petric"
	},
	{
		"id": 215756,
		"name": "Hugo Barbet",
		"name_second": "Hugo Barbet"
	}
]