[
	{
		"id": 48120,
		"name": "Kryvyy Maxym",
		"name_second": "Kryvyy Maxym"
	},
	{
		"id": 252537,
		"name": "Drey Panyalay",
		"name_second": "Drey Panyalay"
	},
	{
		"id": 243566,
		"name": "Roken Tampubolon",
		"name_second": "Roken Tampubolon"
	},
	{
		"id": 245740,
		"name": "Ahmad Ihwan",
		"name_second": "Ahmad Ihwan"
	},
	{
		"id": 113591,
		"name": "Ricky Akbar Ohorella",
		"name_second": "Ricky Akbar Ohorella"
	},
	{
		"id": 177331,
		"name": "Rudi Rudi",
		"name_second": "Rudi Rudi"
	},
	{
		"id": 179179,
		"name": "Hyun Goo Yoo",
		"name_second": "Hyun Goo Yoo"
	},
	{
		"id": 254912,
		"name": "Vivi Asrizal",
		"name_second": "Vivi Asrizal"
	},
	{
		"id": 243568,
		"name": "Dimas Saputra",
		"name_second": "Dimas Saputra"
	},
	{
		"id": 256326,
		"name": "Firman Juliansyah",
		"name_second": "Firman Juliansyah"
	},
	{
		"id": 176050,
		"name": "Rosad Setiawan",
		"name_second": "Rosad Setiawan"
	},
	{
		"id": 256432,
		"name": "Dwiki Arya",
		"name_second": "Dwiki Arya"
	},
	{
		"id": 219116,
		"name": "Risna Prahalabenta",
		"name_second": "Risna Prahalabenta"
	},
	{
		"id": 243565,
		"name": "Wiganda Pradika",
		"name_second": "Wiganda Pradika"
	},
	{
		"id": 176730,
		"name": "Muhammad Rifki",
		"name_second": "Muhammad Rifki"
	},
	{
		"id": 264181,
		"name": "Hadi Ardiansyah",
		"name_second": "Hadi Ardiansyah"
	},
	{
		"id": 113626,
		"name": "Samsidar",
		"name_second": "Samsidar"
	},
	{
		"id": 220360,
		"name": "Fakhrurrazi Quba",
		"name_second": "Fakhrurrazi Quba"
	},
	{
		"id": 245742,
		"name": "Achmad Bachtiar",
		"name_second": "Achmad Bachtiar"
	}
]