[
	{
		"id": 145792,
		"name": "Alim Karkaev",
		"name_second": "Alim Karkaev"
	},
	{
		"id": 245397,
		"name": "Alan Khachirov",
		"name_second": "Alan Khachirov"
	},
	{
		"id": 145796,
		"name": "Azamat Balkarov",
		"name_second": "Azamat Balkarov"
	},
	{
		"id": 180609,
		"name": "Igor Maslennikov",
		"name_second": "Igor Maslennikov"
	},
	{
		"id": 145791,
		"name": "Vladislav Semenov",
		"name_second": "Vladislav Semenov"
	},
	{
		"id": 145789,
		"name": "Timur Teberdiev",
		"name_second": "Timur Teberdiev"
	},
	{
		"id": 113520,
		"name": "Artem Orsaev",
		"name_second": "Artem Orsaev"
	},
	{
		"id": 145784,
		"name": "Imran Kardanov",
		"name_second": "Imran Kardanov"
	}
]