[
	{
		"id": 186115,
		"name": "Hsiung Yuan-Kuan",
		"name_second": "Hsiung Yuan-Kuan"
	},
	{
		"id": 186118,
		"name": "Wu Tung-Yang",
		"name_second": "Wu Tung-Yang"
	},
	{
		"id": 186106,
		"name": "Huang Yu-Ming",
		"name_second": "Huang Yu-Ming"
	},
	{
		"id": 186107,
		"name": "Kuo Chia-Cheng",
		"name_second": "Kuo Chia-Cheng"
	},
	{
		"id": 186108,
		"name": "Chien Peng-Yen",
		"name_second": "Chien Peng-Yen"
	},
	{
		"id": 186109,
		"name": "Chiu Po-Jui",
		"name_second": "Chiu Po-Jui"
	},
	{
		"id": 186110,
		"name": "Lan Hao-Yu",
		"name_second": "Lan Hao-Yu"
	},
	{
		"id": 186111,
		"name": "Li Po-Yu",
		"name_second": "Li Po-Yu"
	},
	{
		"id": 185908,
		"name": "Ma Liang-Cheng",
		"name_second": "Ma Liang-Cheng"
	},
	{
		"id": 186112,
		"name": "Liao Wen-Hao",
		"name_second": "Liao Wen-Hao"
	},
	{
		"id": 186113,
		"name": "Chang Chun-Chieh",
		"name_second": "Chang Chun-Chieh"
	},
	{
		"id": 186114,
		"name": "Shunnosuke Tadokoro",
		"name_second": "Shunnosuke Tadokoro"
	},
	{
		"id": 186119,
		"name": "Liu yuhao",
		"name_second": "Liu yuhao"
	},
	{
		"id": 186101,
		"name": "Wang Chung-Yu",
		"name_second": "Wang Chung-Yu"
	},
	{
		"id": 186102,
		"name": "Cheng Chun-Hsien",
		"name_second": "Cheng Chun-Hsien"
	},
	{
		"id": 186103,
		"name": "Hsieh Peng-Lung",
		"name_second": "Hsieh Peng-Lung"
	},
	{
		"id": 186104,
		"name": "Chang Chia-Wen",
		"name_second": "Chang Chia-Wen"
	},
	{
		"id": 186105,
		"name": "Kuo Ping-Sheng",
		"name_second": "Kuo Ping-Sheng"
	}
]