[
	{
		"id": 199088,
		"name": "Vadym Loboda",
		"name_second": "Vadym Loboda"
	},
	{
		"id": 189115,
		"name": "Ivan Kuts",
		"name_second": "Ivan Kuts"
	},
	{
		"id": 268682,
		"name": "Andriy Globa",
		"name_second": "Andriy Globa"
	},
	{
		"id": 189116,
		"name": "Mykhaylo Udod",
		"name_second": "Mykhaylo Udod"
	},
	{
		"id": 267970,
		"name": "Orest Panchyshyn",
		"name_second": "Orest Panchyshyn"
	},
	{
		"id": 273846,
		"name": "Artem Umanets",
		"name_second": "Artem Umanets"
	},
	{
		"id": 273848,
		"name": "Simon Galoyan",
		"name_second": "Simon Galoyan"
	},
	{
		"id": 199089,
		"name": "Oleksandr Kryvenko",
		"name_second": "Oleksandr Kryvenko"
	},
	{
		"id": 277875,
		"name": "Michael Obamina",
		"name_second": "Michael Obamina"
	},
	{
		"id": 269934,
		"name": "Ivan Palamarchuk",
		"name_second": "Ivan Palamarchuk"
	},
	{
		"id": 189113,
		"name": "Oleksandr Horodenko",
		"name_second": "Oleksandr Horodenko"
	},
	{
		"id": 243054,
		"name": "Davronbek Azizov",
		"name_second": "Davronbek Azizov"
	},
	{
		"id": 278908,
		"name": "Danylo Sydorenko",
		"name_second": "Danylo Sydorenko"
	},
	{
		"id": 246171,
		"name": "Artem Tovkach",
		"name_second": "Artem Tovkach"
	},
	{
		"id": 247246,
		"name": "Yuriy Dudnyk",
		"name_second": "Yuriy Dudnyk"
	},
	{
		"id": 246172,
		"name": "Danylo Arkusha",
		"name_second": "Danylo Arkusha"
	},
	{
		"id": 189110,
		"name": "Andrii Oliinyk",
		"name_second": "Andrii Oliinyk"
	},
	{
		"id": 246173,
		"name": "Oleksii Slutskyi",
		"name_second": "Oleksii Slutskyi"
	},
	{
		"id": 189111,
		"name": "Vladyslav Zakorskyi",
		"name_second": "Vladyslav Zakorskyi"
	}
]