[
	{
		"id": 78724,
		"name": "Barcellos Freda Taison",
		"name_second": "Barcellos Freda Taison"
	},
	{
		"id": 138612,
		"name": "Mbwana Samatta",
		"name_second": "Mbwana Samatta"
	},
	{
		"id": 108484,
		"name": "Brandon Thomas Llamas",
		"name_second": "Brandon Thomas Llamas"
	},
	{
		"id": 234022,
		"name": "Stefanos Tzimas",
		"name_second": "Stefanos Tzimas"
	},
	{
		"id": 100973,
		"name": "Thomas Murg",
		"name_second": "Thomas Murg"
	},
	{
		"id": 116518,
		"name": "Andrija Zivkovic",
		"name_second": "Andrija Zivkovic"
	},
	{
		"id": 104575,
		"name": "Kiril Despodov",
		"name_second": "Kiril Despodov"
	},
	{
		"id": 178131,
		"name": "Theocharis Tsingaras",
		"name_second": "Theocharis Tsingaras"
	},
	{
		"id": 92647,
		"name": "Souahilo Meite",
		"name_second": "Souahilo Meite"
	},
	{
		"id": 85097,
		"name": "Stefan Schwab",
		"name_second": "Stefan Schwab"
	},
	{
		"id": 79746,
		"name": "Magomed Ozdoev",
		"name_second": "Magomed Ozdoev"
	},
	{
		"id": 175460,
		"name": "Marcos Antonio Silva San",
		"name_second": "Marcos Antonio Silva San"
	},
	{
		"id": 203262,
		"name": "Giannis Konstantelias",
		"name_second": "Giannis Konstantelias"
	},
	{
		"id": 203544,
		"name": "Andre Ricardo",
		"name_second": "Andre Ricardo"
	},
	{
		"id": 120023,
		"name": "Ivan Nasberg",
		"name_second": "Ivan Nasberg"
	},
	{
		"id": 222956,
		"name": "Konstantinos Koulierakis",
		"name_second": "Konstantinos Koulierakis"
	},
	{
		"id": 178130,
		"name": "Giannis Michailidis",
		"name_second": "Giannis Michailidis"
	},
	{
		"id": 114912,
		"name": "William Troost-Ekong",
		"name_second": "William Troost-Ekong"
	},
	{
		"id": 103673,
		"name": "Jonathan Castro Otto, Jonny",
		"name_second": "Jonathan Castro Otto, Jonny"
	},
	{
		"id": 69092,
		"name": "Vieirinha Adelino Andre Vieira de Freita",
		"name_second": "Vieirinha Adelino Andre Vieira de Freita"
	},
	{
		"id": 102567,
		"name": "Abdul Rahman Baba",
		"name_second": "Abdul Rahman Baba"
	},
	{
		"id": 128696,
		"name": "Luis Rafael Soares Alves,Rafa",
		"name_second": "Luis Rafael Soares Alves,Rafa"
	},
	{
		"id": 90401,
		"name": "Tomasz Kedziora",
		"name_second": "Tomasz Kedziora"
	},
	{
		"id": 170702,
		"name": "Joan Sastri",
		"name_second": "Joan Sastri"
	},
	{
		"id": 78794,
		"name": "Zivko Zivkovic",
		"name_second": "Zivko Zivkovic"
	},
	{
		"id": 264423,
		"name": "Dimitrios Monastirlis",
		"name_second": "Dimitrios Monastirlis"
	},
	{
		"id": 167342,
		"name": "Dominik Kotarski",
		"name_second": "Dominik Kotarski"
	},
	{
		"id": 202731,
		"name": "Christos Talichmanidis",
		"name_second": "Christos Talichmanidis"
	}
]