[
	{
		"id": 232072,
		"name": "Carlos Gimenez",
		"name_second": "Carlos Gimenez"
	},
	{
		"id": 279916,
		"name": "Sebastian Corrales",
		"name_second": "Sebastian Corrales"
	},
	{
		"id": 127615,
		"name": "Oscar Ruiz",
		"name_second": "Oscar Ruiz"
	},
	{
		"id": 205820,
		"name": "Jose Verdun",
		"name_second": "Jose Verdun"
	},
	{
		"id": 170545,
		"name": "Nicolas Morinigo",
		"name_second": "Nicolas Morinigo"
	},
	{
		"id": 85301,
		"name": "Dario Lezcano",
		"name_second": "Dario Lezcano"
	},
	{
		"id": 231498,
		"name": "Derlis Rodríguez",
		"name_second": "Derlis Rodríguez"
	},
	{
		"id": 71744,
		"name": "Orlando Berrio Melendez",
		"name_second": "Orlando Berrio Melendez"
	},
	{
		"id": 73036,
		"name": "Nestor Abraham Camacho Ledesma",
		"name_second": "Nestor Abraham Camacho Ledesma"
	},
	{
		"id": 231980,
		"name": "Martin Nunez",
		"name_second": "Martin Nunez"
	},
	{
		"id": 231488,
		"name": "Ronal Domínguez",
		"name_second": "Ronal Domínguez"
	},
	{
		"id": 262700,
		"name": "Lucas Romero",
		"name_second": "Lucas Romero"
	},
	{
		"id": 191974,
		"name": "Valdeci Moreira da Silva",
		"name_second": "Valdeci Moreira da Silva"
	},
	{
		"id": 205659,
		"name": "Orlando David Colman",
		"name_second": "Orlando David Colman"
	},
	{
		"id": 205653,
		"name": "Marcelo Miguel Paredes Valdez",
		"name_second": "Marcelo Miguel Paredes Valdez"
	},
	{
		"id": 126494,
		"name": "Nelson Acevedo",
		"name_second": "Nelson Acevedo"
	},
	{
		"id": 265487,
		"name": "Hernan Cano",
		"name_second": "Hernan Cano"
	},
	{
		"id": 241936,
		"name": "Edgar Benitez",
		"name_second": "Edgar Benitez"
	},
	{
		"id": 74185,
		"name": "Marcos Caceres",
		"name_second": "Marcos Caceres"
	},
	{
		"id": 231477,
		"name": "Pablo Espinoza",
		"name_second": "Pablo Espinoza"
	},
	{
		"id": 122048,
		"name": "Luis Cabral",
		"name_second": "Luis Cabral"
	},
	{
		"id": 168294,
		"name": "Helerson Mateus do Nascimento",
		"name_second": "Helerson Mateus do Nascimento"
	},
	{
		"id": 205818,
		"name": "Rodney Miguel Pedrozo",
		"name_second": "Rodney Miguel Pedrozo"
	},
	{
		"id": 118318,
		"name": "Walter Clar",
		"name_second": "Walter Clar"
	},
	{
		"id": 174160,
		"name": "Alexis Fernandez",
		"name_second": "Alexis Fernandez"
	},
	{
		"id": 84024,
		"name": "Victor Ferraz Macedo",
		"name_second": "Victor Ferraz Macedo"
	},
	{
		"id": 205816,
		"name": "Hector Espinola",
		"name_second": "Hector Espinola"
	},
	{
		"id": 231472,
		"name": "Aldo Bareiro",
		"name_second": "Aldo Bareiro"
	},
	{
		"id": 222158,
		"name": "Diego Huesca",
		"name_second": "Diego Huesca"
	}
]