[
	{
		"id": 244761,
		"name": "Amiran Dzagania",
		"name_second": "Amiran Dzagania"
	},
	{
		"id": 194279,
		"name": "Giga Bechvaia",
		"name_second": "Giga Bechvaia"
	},
	{
		"id": 248206,
		"name": "Beka Gugberidze",
		"name_second": "Beka Gugberidze"
	},
	{
		"id": 275281,
		"name": "Zurab Adeishvili",
		"name_second": "Zurab Adeishvili"
	},
	{
		"id": 264191,
		"name": "Sergi Abramishvili",
		"name_second": "Sergi Abramishvili"
	},
	{
		"id": 194275,
		"name": "Giorgi Kvaginadze",
		"name_second": "Giorgi Kvaginadze"
	},
	{
		"id": 194280,
		"name": "Giorgi Melkadze",
		"name_second": "Giorgi Melkadze"
	},
	{
		"id": 251098,
		"name": "Shakro Dvalishvili",
		"name_second": "Shakro Dvalishvili"
	},
	{
		"id": 264188,
		"name": "Luka Tolordava",
		"name_second": "Luka Tolordava"
	},
	{
		"id": 264186,
		"name": "Ilia Gulisashvili",
		"name_second": "Ilia Gulisashvili"
	},
	{
		"id": 248165,
		"name": "Nika Ketselashvili",
		"name_second": "Nika Ketselashvili"
	},
	{
		"id": 264771,
		"name": "Irakli Javakhishvili",
		"name_second": "Irakli Javakhishvili"
	},
	{
		"id": 246965,
		"name": "Sulkhan Svianadze",
		"name_second": "Sulkhan Svianadze"
	},
	{
		"id": 251094,
		"name": "Giorgi Samadashvili",
		"name_second": "Giorgi Samadashvili"
	},
	{
		"id": 270319,
		"name": "Guram Kharebava",
		"name_second": "Guram Kharebava"
	},
	{
		"id": 279587,
		"name": "Temur Dalakishvili",
		"name_second": "Temur Dalakishvili"
	},
	{
		"id": 194271,
		"name": "Alex Kaishauri",
		"name_second": "Alex Kaishauri"
	},
	{
		"id": 251096,
		"name": "Luka Berozashvili",
		"name_second": "Luka Berozashvili"
	},
	{
		"id": 246967,
		"name": "Dimitri Kupreishvili",
		"name_second": "Dimitri Kupreishvili"
	},
	{
		"id": 246948,
		"name": "Tornike Shekiladze",
		"name_second": "Tornike Shekiladze"
	},
	{
		"id": 23370,
		"name": "Grigol Bediashvili",
		"name_second": "Grigol Bediashvili"
	},
	{
		"id": 264859,
		"name": "Davit Iobashvili",
		"name_second": "Davit Iobashvili"
	},
	{
		"id": 279627,
		"name": "Avto Kapanadze",
		"name_second": "Avto Kapanadze"
	}
]