[
	{
		"id": 94237,
		"name": "Michael Hurlimann",
		"name_second": "Michael Hurlimann"
	},
	{
		"id": 94238,
		"name": "Valdet Istrefi",
		"name_second": "Valdet Istrefi"
	},
	{
		"id": 262321,
		"name": "Sofian Domoraud Operi",
		"name_second": "Sofian Domoraud Operi"
	},
	{
		"id": 97227,
		"name": "Samel Sabanovic",
		"name_second": "Samel Sabanovic"
	},
	{
		"id": 78630,
		"name": "Carlos De Oliveira Silvio",
		"name_second": "Carlos De Oliveira Silvio"
	},
	{
		"id": 101832,
		"name": "Pedro Jose Martin Moreno",
		"name_second": "Pedro Jose Martin Moreno"
	},
	{
		"id": 94241,
		"name": "Christian Bohi",
		"name_second": "Christian Bohi"
	},
	{
		"id": 94242,
		"name": "Fabian Steuri",
		"name_second": "Fabian Steuri"
	},
	{
		"id": 65635,
		"name": "Thomas Knopfel",
		"name_second": "Thomas Knopfel"
	},
	{
		"id": 94243,
		"name": "Francesco Clemente",
		"name_second": "Francesco Clemente"
	},
	{
		"id": 89803,
		"name": "Florian Eberle",
		"name_second": "Florian Eberle"
	},
	{
		"id": 94244,
		"name": "Lulzim Mehmeti",
		"name_second": "Lulzim Mehmeti"
	},
	{
		"id": 247295,
		"name": "Dario Stadler",
		"name_second": "Dario Stadler"
	},
	{
		"id": 94245,
		"name": "Florian Steiger",
		"name_second": "Florian Steiger"
	},
	{
		"id": 65153,
		"name": "Boris Prokopic",
		"name_second": "Boris Prokopic"
	},
	{
		"id": 179252,
		"name": "Mergim Bajrami",
		"name_second": "Mergim Bajrami"
	},
	{
		"id": 94249,
		"name": "Alexandre Edilson de Freitas",
		"name_second": "Alexandre Edilson de Freitas"
	},
	{
		"id": 260683,
		"name": "Josip Lovakovic",
		"name_second": "Josip Lovakovic"
	},
	{
		"id": 94251,
		"name": "Adrian Inauen",
		"name_second": "Adrian Inauen"
	},
	{
		"id": 94252,
		"name": "Thomas Inauen",
		"name_second": "Thomas Inauen"
	},
	{
		"id": 94254,
		"name": "Vincenz Lazraj",
		"name_second": "Vincenz Lazraj"
	},
	{
		"id": 65644,
		"name": "Marc Zellweger",
		"name_second": "Marc Zellweger"
	},
	{
		"id": 263939,
		"name": "Bung Tsai Freimann",
		"name_second": "Bung Tsai Freimann"
	},
	{
		"id": 247296,
		"name": "Giosue Capozzi",
		"name_second": "Giosue Capozzi"
	},
	{
		"id": 94255,
		"name": "Michael Keller",
		"name_second": "Michael Keller"
	},
	{
		"id": 94256,
		"name": "Philip Zuger",
		"name_second": "Philip Zuger"
	},
	{
		"id": 179119,
		"name": "Marin Cavar",
		"name_second": "Marin Cavar"
	},
	{
		"id": 94257,
		"name": "Arif Celebi",
		"name_second": "Arif Celebi"
	}
]