[
	{
		"id": 276183,
		"name": "Emmanuel Annor",
		"name_second": "Emmanuel Annor"
	},
	{
		"id": 252813,
		"name": "Cephas Mantey",
		"name_second": "Cephas Mantey"
	},
	{
		"id": 262444,
		"name": "Clinton Duodu",
		"name_second": "Clinton Duodu"
	},
	{
		"id": 278126,
		"name": "Adukwaw Boadi Ebenezer",
		"name_second": "Adukwaw Boadi Ebenezer"
	},
	{
		"id": 280603,
		"name": "Isaiah Nyarko",
		"name_second": "Isaiah Nyarko"
	},
	{
		"id": 246039,
		"name": "Gabriel Tenlep",
		"name_second": "Gabriel Tenlep"
	},
	{
		"id": 254286,
		"name": "Francis Acquah",
		"name_second": "Francis Acquah"
	},
	{
		"id": 252748,
		"name": "Samuel Osei Kuffour",
		"name_second": "Samuel Osei Kuffour"
	},
	{
		"id": 271418,
		"name": "Emmanuel Ababio",
		"name_second": "Emmanuel Ababio"
	},
	{
		"id": 265307,
		"name": "Joseph Kinful",
		"name_second": "Joseph Kinful"
	},
	{
		"id": 272421,
		"name": "Dari Aziz",
		"name_second": "Dari Aziz"
	}
]