[
	{
		"id": 232858,
		"name": "Michalis Kolias",
		"name_second": "Michalis Kolias"
	},
	{
		"id": 161030,
		"name": "Ahmad Mendes Moreira",
		"name_second": "Ahmad Mendes Moreira"
	},
	{
		"id": 217966,
		"name": "Evangelos Andreou",
		"name_second": "Evangelos Andreou"
	},
	{
		"id": 145965,
		"name": "Jonathan Morsay",
		"name_second": "Jonathan Morsay"
	},
	{
		"id": 230111,
		"name": "Rafa.",
		"name_second": "Rafa."
	},
	{
		"id": 113794,
		"name": "Nicolae Milinceanu",
		"name_second": "Nicolae Milinceanu"
	},
	{
		"id": 79226,
		"name": "Saido Berahino",
		"name_second": "Saido Berahino"
	},
	{
		"id": 123515,
		"name": "Georgi Minchev",
		"name_second": "Georgi Minchev"
	},
	{
		"id": 79085,
		"name": "Alexander Kacaniklic",
		"name_second": "Alexander Kacaniklic"
	},
	{
		"id": 180228,
		"name": "Fabrice Kah Nkwoh",
		"name_second": "Fabrice Kah Nkwoh"
	},
	{
		"id": 20874,
		"name": "Kevin Mirallas",
		"name_second": "Kevin Mirallas"
	},
	{
		"id": 109862,
		"name": "Andreas Makris",
		"name_second": "Andreas Makris"
	},
	{
		"id": 262099,
		"name": "Themistoklis Themistokleous",
		"name_second": "Themistoklis Themistokleous"
	},
	{
		"id": 157773,
		"name": "Vasilios Papafotis",
		"name_second": "Vasilios Papafotis"
	},
	{
		"id": 117351,
		"name": "Slavoljub Srnic",
		"name_second": "Slavoljub Srnic"
	},
	{
		"id": 124649,
		"name": "Javier Osvaldo Mendoza",
		"name_second": "Javier Osvaldo Mendoza"
	},
	{
		"id": 169007,
		"name": "Evdoras Silvestros",
		"name_second": "Evdoras Silvestros"
	},
	{
		"id": 86295,
		"name": "Slobodan Medojevic",
		"name_second": "Slobodan Medojevic"
	},
	{
		"id": 129328,
		"name": "Hugo Basto",
		"name_second": "Hugo Basto"
	},
	{
		"id": 80293,
		"name": "Petar Filipovic",
		"name_second": "Petar Filipovic"
	},
	{
		"id": 230114,
		"name": "Kristian Bilovar",
		"name_second": "Kristian Bilovar"
	},
	{
		"id": 205036,
		"name": "Kypros Neofytou",
		"name_second": "Kypros Neofytou"
	},
	{
		"id": 198205,
		"name": "Djalma Antonio da Silva Filho",
		"name_second": "Djalma Antonio da Silva Filho"
	},
	{
		"id": 133190,
		"name": "Ravy Tsouka Dozi",
		"name_second": "Ravy Tsouka Dozi"
	},
	{
		"id": 217964,
		"name": "Christoforos Frantzis",
		"name_second": "Christoforos Frantzis"
	},
	{
		"id": 103456,
		"name": "Giannis Anestis",
		"name_second": "Giannis Anestis"
	},
	{
		"id": 105460,
		"name": "Miguel Oliveira",
		"name_second": "Miguel Oliveira"
	},
	{
		"id": 230116,
		"name": "Michalis Kyriakou",
		"name_second": "Michalis Kyriakou"
	}
]