[
	{
		"id": 155094,
		"name": "Sasa Kalajdzic",
		"name_second": "Sasa Kalajdzic"
	},
	{
		"id": 223946,
		"name": "Fares Chaibi",
		"name_second": "Fares Chaibi"
	},
	{
		"id": 228258,
		"name": "Jean Négoce",
		"name_second": "Jean Négoce"
	},
	{
		"id": 186855,
		"name": "Omar Marmoush",
		"name_second": "Omar Marmoush"
	},
	{
		"id": 201001,
		"name": "Hugo Ekitike",
		"name_second": "Hugo Ekitike"
	},
	{
		"id": 232984,
		"name": "Nacho Ferri",
		"name_second": "Nacho Ferri"
	},
	{
		"id": 130345,
		"name": "Donny van de Beek",
		"name_second": "Donny van de Beek"
	},
	{
		"id": 224779,
		"name": "Hugo Emanuel Larsson",
		"name_second": "Hugo Emanuel Larsson"
	},
	{
		"id": 37594,
		"name": "Sebastian Rode",
		"name_second": "Sebastian Rode"
	},
	{
		"id": 177630,
		"name": "Eric Junior Dina Ebimbe",
		"name_second": "Eric Junior Dina Ebimbe"
	},
	{
		"id": 227888,
		"name": "Mehdi Loune",
		"name_second": "Mehdi Loune"
	},
	{
		"id": 80233,
		"name": "Mario Gotze",
		"name_second": "Mario Gotze"
	},
	{
		"id": 124461,
		"name": "Ellyes Skhiri",
		"name_second": "Ellyes Skhiri"
	},
	{
		"id": 200987,
		"name": "Ansgar Knauff",
		"name_second": "Ansgar Knauff"
	},
	{
		"id": 241010,
		"name": "Elias Baum",
		"name_second": "Elias Baum"
	},
	{
		"id": 184563,
		"name": "Willian Joel Pacho Tenorio",
		"name_second": "Willian Joel Pacho Tenorio"
	},
	{
		"id": 126509,
		"name": "Robin Koch",
		"name_second": "Robin Koch"
	},
	{
		"id": 175602,
		"name": "Hrvoje Smolcic",
		"name_second": "Hrvoje Smolcic"
	},
	{
		"id": 495,
		"name": "Makoto HASEBE",
		"name_second": "Makoto HASEBE"
	},
	{
		"id": 201612,
		"name": "Nnamdi Collins",
		"name_second": "Nnamdi Collins"
	},
	{
		"id": 171006,
		"name": "Lucas Silva Melo,Tuta",
		"name_second": "Lucas Silva Melo,Tuta"
	},
	{
		"id": 233117,
		"name": "Davis Bautista",
		"name_second": "Davis Bautista"
	},
	{
		"id": 235967,
		"name": "Dario Gebuhr",
		"name_second": "Dario Gebuhr"
	},
	{
		"id": 182250,
		"name": "Niels Nkounkou",
		"name_second": "Niels Nkounkou"
	},
	{
		"id": 102176,
		"name": "Philipp Max",
		"name_second": "Philipp Max"
	},
	{
		"id": 38376,
		"name": "Timothy Chandler",
		"name_second": "Timothy Chandler"
	},
	{
		"id": 144863,
		"name": "Aurelio Buta",
		"name_second": "Aurelio Buta"
	},
	{
		"id": 39925,
		"name": "Kevin Trapp",
		"name_second": "Kevin Trapp"
	},
	{
		"id": 30096,
		"name": "Jens Grahl",
		"name_second": "Jens Grahl"
	},
	{
		"id": 244692,
		"name": "Nils Ramming",
		"name_second": "Nils Ramming"
	},
	{
		"id": 230784,
		"name": "Kaua Santos",
		"name_second": "Kaua Santos"
	},
	{
		"id": 226936,
		"name": "Simon Simoni",
		"name_second": "Simon Simoni"
	},
	{
		"id": 240643,
		"name": "Luke Gauer",
		"name_second": "Luke Gauer"
	}
]