[
	{
		"id": 186582,
		"name": "Komron Mirzonazhod",
		"name_second": "Komron Mirzonazhod"
	},
	{
		"id": 186583,
		"name": "Bakhtiyor Choriev",
		"name_second": "Bakhtiyor Choriev"
	},
	{
		"id": 186585,
		"name": "Abdusamad Samadov",
		"name_second": "Abdusamad Samadov"
	},
	{
		"id": 186586,
		"name": "Sarvar Rihsiboev",
		"name_second": "Sarvar Rihsiboev"
	},
	{
		"id": 186587,
		"name": "Sharafjon Solehov",
		"name_second": "Sharafjon Solehov"
	},
	{
		"id": 240944,
		"name": "Shukhratdzhon Shonazarov",
		"name_second": "Shukhratdzhon Shonazarov"
	},
	{
		"id": 186578,
		"name": "Parviz Bokiev",
		"name_second": "Parviz Bokiev"
	},
	{
		"id": 250756,
		"name": "S. Ofori",
		"name_second": "S. Ofori"
	},
	{
		"id": 186579,
		"name": "Sirozh Khamraev",
		"name_second": "Sirozh Khamraev"
	},
	{
		"id": 186580,
		"name": "Firdavs Chakalov",
		"name_second": "Firdavs Chakalov"
	},
	{
		"id": 186581,
		"name": "Alisher Barotov",
		"name_second": "Alisher Barotov"
	},
	{
		"id": 182030,
		"name": "Khurshed Beknazarov",
		"name_second": "Khurshed Beknazarov"
	},
	{
		"id": 186577,
		"name": "Daler Barotov",
		"name_second": "Daler Barotov"
	}
]