[
	{
		"id": 89270,
		"name": "Kristaps Blanks",
		"name_second": "Kristaps Blanks"
	},
	{
		"id": 132837,
		"name": "Nikita Ivanovs",
		"name_second": "Nikita Ivanovs"
	},
	{
		"id": 46612,
		"name": "Juris Laizans",
		"name_second": "Juris Laizans"
	},
	{
		"id": 59880,
		"name": "Aleksejs Visnakovs",
		"name_second": "Aleksejs Visnakovs"
	},
	{
		"id": 22403,
		"name": "Aleksandrs Isakovs",
		"name_second": "Aleksandrs Isakovs"
	},
	{
		"id": 89278,
		"name": "Vadims Gailus",
		"name_second": "Vadims Gailus"
	},
	{
		"id": 85359,
		"name": "Renars Rode",
		"name_second": "Renars Rode"
	},
	{
		"id": 22398,
		"name": "Mihails Zemlinskis",
		"name_second": "Mihails Zemlinskis"
	},
	{
		"id": 131326,
		"name": "Nikita Berenfelds",
		"name_second": "Nikita Berenfelds"
	},
	{
		"id": 89261,
		"name": "Oleg Timofejev",
		"name_second": "Oleg Timofejev"
	},
	{
		"id": 102829,
		"name": "Pavels Dorosevs",
		"name_second": "Pavels Dorosevs"
	}
]