[
	{
		"id": 31528,
		"name": "Boubacar Kebe",
		"name_second": "Boubacar Kebe"
	},
	{
		"id": 172507,
		"name": "Arman Ramezani",
		"name_second": "Arman Ramezani"
	},
	{
		"id": 130836,
		"name": "Amir Arsalan Motahari",
		"name_second": "Amir Arsalan Motahari"
	},
	{
		"id": 209652,
		"name": "Sobhan Khaghani",
		"name_second": "Sobhan Khaghani"
	},
	{
		"id": 168350,
		"name": "Rouhollah Bagheri",
		"name_second": "Rouhollah Bagheri"
	},
	{
		"id": 203960,
		"name": "Jafar Salmani",
		"name_second": "Jafar Salmani"
	},
	{
		"id": 157247,
		"name": "Kevin Yamga",
		"name_second": "Kevin Yamga"
	},
	{
		"id": 83207,
		"name": "Gustavo Blanco Leschuk",
		"name_second": "Gustavo Blanco Leschuk"
	},
	{
		"id": 31594,
		"name": "Rudy Gestede",
		"name_second": "Rudy Gestede"
	},
	{
		"id": 187149,
		"name": "Peyman Babaei",
		"name_second": "Peyman Babaei"
	},
	{
		"id": 144514,
		"name": "Mehrdad Mohammadi",
		"name_second": "Mehrdad Mohammadi"
	},
	{
		"id": 143642,
		"name": "Reza Mirzaei",
		"name_second": "Reza Mirzaei"
	},
	{
		"id": 143269,
		"name": "Mehdi Mehdipour",
		"name_second": "Mehdi Mehdipour"
	},
	{
		"id": 164714,
		"name": "Vouria Ghafoori",
		"name_second": "Vouria Ghafoori"
	},
	{
		"id": 115585,
		"name": "Abedini Fardin",
		"name_second": "Abedini Fardin"
	},
	{
		"id": 151055,
		"name": "Seyed Mohsen Karimi",
		"name_second": "Seyed Mohsen Karimi"
	},
	{
		"id": 3213,
		"name": "Goran Lovre",
		"name_second": "Goran Lovre"
	},
	{
		"id": 169415,
		"name": "Reza Azari",
		"name_second": "Reza Azari"
	},
	{
		"id": 136046,
		"name": "Arash Rezavand",
		"name_second": "Arash Rezavand"
	},
	{
		"id": 96518,
		"name": "Khosro Heydari",
		"name_second": "Khosro Heydari"
	},
	{
		"id": 162419,
		"name": "Mohammad Hossein Moradmand",
		"name_second": "Mohammad Hossein Moradmand"
	},
	{
		"id": 99005,
		"name": "Mohammad Gholami",
		"name_second": "Mohammad Gholami"
	},
	{
		"id": 80025,
		"name": "Hrvoje Milic",
		"name_second": "Hrvoje Milic"
	},
	{
		"id": 52202,
		"name": "Pejman Montazeri",
		"name_second": "Pejman Montazeri"
	},
	{
		"id": 149670,
		"name": "Armin Sohrabian",
		"name_second": "Armin Sohrabian"
	},
	{
		"id": 165215,
		"name": "Omid Norafkan",
		"name_second": "Omid Norafkan"
	}
]