[
	{
		"id": 279551,
		"name": "Alfredo Chirinos",
		"name_second": "Alfredo Chirinos"
	},
	{
		"id": 210129,
		"name": "Josue Rodriguez",
		"name_second": "Josue Rodriguez"
	},
	{
		"id": 152570,
		"name": "Maximiliano Freitas",
		"name_second": "Maximiliano Freitas"
	},
	{
		"id": 214041,
		"name": "Luis Plaza",
		"name_second": "Luis Plaza"
	},
	{
		"id": 214044,
		"name": "Roy Rodriguez",
		"name_second": "Roy Rodriguez"
	},
	{
		"id": 275219,
		"name": "Kevin Redondo",
		"name_second": "Kevin Redondo"
	},
	{
		"id": 227910,
		"name": "Alessandro Del Piero Moreno",
		"name_second": "Alessandro Del Piero Moreno"
	},
	{
		"id": 275220,
		"name": "Victor Ramirez",
		"name_second": "Victor Ramirez"
	},
	{
		"id": 278103,
		"name": "Jorchs Olaya",
		"name_second": "Jorchs Olaya"
	},
	{
		"id": 116945,
		"name": "Oscar Vilchez",
		"name_second": "Oscar Vilchez"
	},
	{
		"id": 214033,
		"name": "Mauricio Sandoval",
		"name_second": "Mauricio Sandoval"
	},
	{
		"id": 184606,
		"name": "Felipe Mesones",
		"name_second": "Felipe Mesones"
	},
	{
		"id": 143833,
		"name": "Regis Martin Quiroz Ampuer",
		"name_second": "Regis Martin Quiroz Ampuer"
	}
]