[
	{
		"id": 153997,
		"name": "Maximiliano Salas",
		"name_second": "Maximiliano Salas"
	},
	{
		"id": 96702,
		"name": "Adrian Martinez",
		"name_second": "Adrian Martinez"
	},
	{
		"id": 121631,
		"name": "Roger Martinez",
		"name_second": "Roger Martinez"
	},
	{
		"id": 162465,
		"name": "Johan Carbonero",
		"name_second": "Johan Carbonero"
	},
	{
		"id": 171292,
		"name": "Agustin Urzi",
		"name_second": "Agustin Urzi"
	},
	{
		"id": 236409,
		"name": "Ramiro Degregorio",
		"name_second": "Ramiro Degregorio"
	},
	{
		"id": 226929,
		"name": "Roman Fernandez",
		"name_second": "Roman Fernandez"
	},
	{
		"id": 179555,
		"name": "Juan Ignacio Martin Nardoni",
		"name_second": "Juan Ignacio Martin Nardoni"
	},
	{
		"id": 72075,
		"name": "Juan Quintero",
		"name_second": "Juan Quintero"
	},
	{
		"id": 168377,
		"name": "Santiago Sosa",
		"name_second": "Santiago Sosa"
	},
	{
		"id": 130022,
		"name": "Leonel Miranda",
		"name_second": "Leonel Miranda"
	},
	{
		"id": 236512,
		"name": "Baltasar Gallego Rodriguez",
		"name_second": "Baltasar Gallego Rodriguez"
	},
	{
		"id": 209968,
		"name": "Santiago Solari",
		"name_second": "Santiago Solari"
	},
	{
		"id": 237091,
		"name": "Santino Vera",
		"name_second": "Santino Vera"
	},
	{
		"id": 164685,
		"name": "Agustin Almendra",
		"name_second": "Agustin Almendra"
	},
	{
		"id": 83093,
		"name": "Bruno Zuculini",
		"name_second": "Bruno Zuculini"
	},
	{
		"id": 239743,
		"name": "David Gonzalez",
		"name_second": "David Gonzalez"
	},
	{
		"id": 140821,
		"name": "Agustin Garcia",
		"name_second": "Agustin Garcia"
	},
	{
		"id": 202543,
		"name": "Marco Di Cesare",
		"name_second": "Marco Di Cesare"
	},
	{
		"id": 66814,
		"name": "Ivan Alexis Pillud",
		"name_second": "Ivan Alexis Pillud"
	},
	{
		"id": 177705,
		"name": "Nazareno Colombo",
		"name_second": "Nazareno Colombo"
	},
	{
		"id": 192046,
		"name": "Gaston Nicolas Martirena Torres",
		"name_second": "Gaston Nicolas Martirena Torres"
	},
	{
		"id": 129342,
		"name": "German Conti",
		"name_second": "German Conti"
	},
	{
		"id": 149752,
		"name": "Gabriel Rojas",
		"name_second": "Gabriel Rojas"
	},
	{
		"id": 74539,
		"name": "Leonardo German Sigali",
		"name_second": "Leonardo German Sigali"
	},
	{
		"id": 173508,
		"name": "Facundo Mura",
		"name_second": "Facundo Mura"
	},
	{
		"id": 232408,
		"name": "Santiago Quiros",
		"name_second": "Santiago Quiros"
	},
	{
		"id": 238104,
		"name": "Tob&#237;as Rubio",
		"name_second": "Tob&#237;as Rubio"
	},
	{
		"id": 210110,
		"name": "Ignacio Galvan",
		"name_second": "Ignacio Galvan"
	},
	{
		"id": 237394,
		"name": "Roberto Le&#243;n",
		"name_second": "Roberto Le&#243;n"
	},
	{
		"id": 82755,
		"name": "Gabriel Arias",
		"name_second": "Gabriel Arias"
	},
	{
		"id": 142172,
		"name": "Facundo Cambeses",
		"name_second": "Facundo Cambeses"
	},
	{
		"id": 277933,
		"name": "Francisco Gomez",
		"name_second": "Francisco Gomez"
	}
]