[
	{
		"id": 260611,
		"name": "Mokibelo Ramabu",
		"name_second": "Mokibelo Ramabu"
	},
	{
		"id": 163334,
		"name": "Dominic Chungwa",
		"name_second": "Dominic Chungwa"
	},
	{
		"id": 254193,
		"name": "Ndamulelo Maphangule",
		"name_second": "Ndamulelo Maphangule"
	},
	{
		"id": 254177,
		"name": "Douglas Mapfumo",
		"name_second": "Douglas Mapfumo"
	},
	{
		"id": 150056,
		"name": "Tshepo Matsemela",
		"name_second": "Tshepo Matsemela"
	},
	{
		"id": 118175,
		"name": "Puleng Tlolane",
		"name_second": "Puleng Tlolane"
	},
	{
		"id": 89287,
		"name": "Ndumiso Mabena",
		"name_second": "Ndumiso Mabena"
	},
	{
		"id": 168361,
		"name": "Joseph Mhlongo",
		"name_second": "Joseph Mhlongo"
	},
	{
		"id": 140046,
		"name": "Andile Eugene Fikizolo",
		"name_second": "Andile Eugene Fikizolo"
	},
	{
		"id": 242998,
		"name": "Tholo Matuludi",
		"name_second": "Tholo Matuludi"
	},
	{
		"id": 260636,
		"name": "Tlou Nkwe",
		"name_second": "Tlou Nkwe"
	},
	{
		"id": 254491,
		"name": "Luciano Van Heerden",
		"name_second": "Luciano Van Heerden"
	},
	{
		"id": 89675,
		"name": "Jabu Percy Maluleke",
		"name_second": "Jabu Percy Maluleke"
	},
	{
		"id": 261996,
		"name": "Stevens Goovadia",
		"name_second": "Stevens Goovadia"
	},
	{
		"id": 196124,
		"name": "Sifiso Mokiti",
		"name_second": "Sifiso Mokiti"
	},
	{
		"id": 244455,
		"name": "Lebohang Nkaki",
		"name_second": "Lebohang Nkaki"
	},
	{
		"id": 152965,
		"name": "Vusimusi Tebogo Mngomezulu",
		"name_second": "Vusimusi Tebogo Mngomezulu"
	},
	{
		"id": 148999,
		"name": "Given Mashikinya",
		"name_second": "Given Mashikinya"
	},
	{
		"id": 179195,
		"name": "Manuel Kambala",
		"name_second": "Manuel Kambala"
	},
	{
		"id": 94069,
		"name": "Lucky Baloyi",
		"name_second": "Lucky Baloyi"
	},
	{
		"id": 260615,
		"name": "Bulelani Nikani",
		"name_second": "Bulelani Nikani"
	},
	{
		"id": 148241,
		"name": "Sibusiso Mbonani",
		"name_second": "Sibusiso Mbonani"
	},
	{
		"id": 105413,
		"name": "Thabiso Semenya",
		"name_second": "Thabiso Semenya"
	},
	{
		"id": 99963,
		"name": "Walter Maponyane",
		"name_second": "Walter Maponyane"
	},
	{
		"id": 252507,
		"name": "Langelihle Ndlovu",
		"name_second": "Langelihle Ndlovu"
	},
	{
		"id": 254198,
		"name": "Manuel Sapunga",
		"name_second": "Manuel Sapunga"
	},
	{
		"id": 196125,
		"name": "Themba Chuma",
		"name_second": "Themba Chuma"
	},
	{
		"id": 196118,
		"name": "Lehlohonolo Phali",
		"name_second": "Lehlohonolo Phali"
	}
]