[
	{
		"id": 187022,
		"name": "Semen Belyakov",
		"name_second": "Semen Belyakov"
	},
	{
		"id": 187023,
		"name": "Rejal Alijev",
		"name_second": "Rejal Alijev"
	},
	{
		"id": 242830,
		"name": "Martin Eensalu",
		"name_second": "Martin Eensalu"
	},
	{
		"id": 132354,
		"name": "Denis Vnukov",
		"name_second": "Denis Vnukov"
	},
	{
		"id": 187019,
		"name": "Kirill Vinogradov",
		"name_second": "Kirill Vinogradov"
	},
	{
		"id": 241368,
		"name": "Leonid Arhipov",
		"name_second": "Leonid Arhipov"
	},
	{
		"id": 187021,
		"name": "Nikolay Mashichev",
		"name_second": "Nikolay Mashichev"
	},
	{
		"id": 187014,
		"name": "Dmitri Kovtunovits",
		"name_second": "Dmitri Kovtunovits"
	},
	{
		"id": 86808,
		"name": "Aleksandr Volodin",
		"name_second": "Aleksandr Volodin"
	},
	{
		"id": 241367,
		"name": "Mark-Antonio Havier",
		"name_second": "Mark-Antonio Havier"
	},
	{
		"id": 187016,
		"name": "Jevgeni Baranov",
		"name_second": "Jevgeni Baranov"
	},
	{
		"id": 187017,
		"name": "Vsevolod Zassuhhin",
		"name_second": "Vsevolod Zassuhhin"
	},
	{
		"id": 187024,
		"name": "Eduard Orehov",
		"name_second": "Eduard Orehov"
	}
]