[
	{
		"id": 41294,
		"name": "Tomas Eriksson",
		"name_second": "Tomas Eriksson"
	},
	{
		"id": 89172,
		"name": "Isa Bagci",
		"name_second": "Isa Bagci"
	},
	{
		"id": 41296,
		"name": "Mathias Gravem",
		"name_second": "Mathias Gravem"
	},
	{
		"id": 41297,
		"name": "Julio Cesar Mosele",
		"name_second": "Julio Cesar Mosele"
	},
	{
		"id": 41300,
		"name": "Mattias Bulun",
		"name_second": "Mattias Bulun"
	},
	{
		"id": 41302,
		"name": "Marco Silva",
		"name_second": "Marco Silva"
	},
	{
		"id": 82309,
		"name": "Christopher Bratt",
		"name_second": "Christopher Bratt"
	},
	{
		"id": 41304,
		"name": "Daniel Ljungholm",
		"name_second": "Daniel Ljungholm"
	},
	{
		"id": 41307,
		"name": "Ante Maletic",
		"name_second": "Ante Maletic"
	},
	{
		"id": 41308,
		"name": "Joakim Jensen",
		"name_second": "Joakim Jensen"
	},
	{
		"id": 41309,
		"name": "Rickard Johansson",
		"name_second": "Rickard Johansson"
	},
	{
		"id": 82310,
		"name": "Robin Edvardsen",
		"name_second": "Robin Edvardsen"
	},
	{
		"id": 41312,
		"name": "Johan Bjorkeryd",
		"name_second": "Johan Bjorkeryd"
	}
]