[
	{
		"id": 255942,
		"name": "Mateo Levy",
		"name_second": "Mateo Levy"
	},
	{
		"id": 183756,
		"name": "Carlos Rodolfo Rotondi",
		"name_second": "Carlos Rodolfo Rotondi"
	},
	{
		"id": 165314,
		"name": "Gabriel Matias Fernandez Leites",
		"name_second": "Gabriel Matias Fernandez Leites"
	},
	{
		"id": 157763,
		"name": "Uriel Antuna",
		"name_second": "Uriel Antuna"
	},
	{
		"id": 86640,
		"name": "Angel Baltazar Sepulveda Sanchez",
		"name_second": "Angel Baltazar Sepulveda Sanchez"
	},
	{
		"id": 209027,
		"name": "Rodrigo Huescas",
		"name_second": "Rodrigo Huescas"
	},
	{
		"id": 273957,
		"name": "Louis Estrada Derbez",
		"name_second": "Louis Estrada Derbez"
	},
	{
		"id": 83898,
		"name": "Lorenzo Faravelli",
		"name_second": "Lorenzo Faravelli"
	},
	{
		"id": 172351,
		"name": "Alexis Hazael Gutierrez Torres",
		"name_second": "Alexis Hazael Gutierrez Torres"
	},
	{
		"id": 167480,
		"name": "Carlos Rodriguez",
		"name_second": "Carlos Rodriguez"
	},
	{
		"id": 169104,
		"name": "Cristian Jimenez",
		"name_second": "Cristian Jimenez"
	},
	{
		"id": 169837,
		"name": "Erik Antonio Lira Mendez",
		"name_second": "Erik Antonio Lira Mendez"
	},
	{
		"id": 72663,
		"name": "Jesus Alberto Duenas Manzo",
		"name_second": "Jesus Alberto Duenas Manzo"
	},
	{
		"id": 129468,
		"name": "Jose Ignacio Rivero Segade",
		"name_second": "Jose Ignacio Rivero Segade"
	},
	{
		"id": 172349,
		"name": "Willer Emilio Ditta Perez",
		"name_second": "Willer Emilio Ditta Perez"
	},
	{
		"id": 238815,
		"name": "Amaury Morales",
		"name_second": "Amaury Morales"
	},
	{
		"id": 218951,
		"name": "Rafael Guerrero Ramirez",
		"name_second": "Rafael Guerrero Ramirez"
	},
	{
		"id": 110581,
		"name": "Carlos Salcedo",
		"name_second": "Carlos Salcedo"
	},
	{
		"id": 237846,
		"name": "Luis Iturbide",
		"name_second": "Luis Iturbide"
	},
	{
		"id": 237845,
		"name": "Alan Zubiri",
		"name_second": "Alan Zubiri"
	},
	{
		"id": 159841,
		"name": "Camilo Candido",
		"name_second": "Camilo Candido"
	},
	{
		"id": 155209,
		"name": "Carlos Vargas",
		"name_second": "Carlos Vargas"
	},
	{
		"id": 129293,
		"name": "Gonzalo Piovi",
		"name_second": "Gonzalo Piovi"
	},
	{
		"id": 178388,
		"name": "Andres Gudino",
		"name_second": "Andres Gudino"
	},
	{
		"id": 173048,
		"name": "Kevin Mier",
		"name_second": "Kevin Mier"
	}
]