[
	{
		"id": 124669,
		"name": "Antonio Rogerio Silva Oliveira,Indio",
		"name_second": "Antonio Rogerio Silva Oliveira,Indio"
	},
	{
		"id": 125039,
		"name": "Rafael Henrique Assis Cardoso",
		"name_second": "Rafael Henrique Assis Cardoso"
	},
	{
		"id": 132566,
		"name": "Andre Filipe Fernandes Nogueira",
		"name_second": "Andre Filipe Fernandes Nogueira"
	},
	{
		"id": 35474,
		"name": "Hugo Miguel Vieira",
		"name_second": "Hugo Miguel Vieira"
	},
	{
		"id": 89585,
		"name": "Rui Manuel Castanheira do Rego",
		"name_second": "Rui Manuel Castanheira do Rego"
	},
	{
		"id": 35170,
		"name": "Bruno Miguel Silva Jorge",
		"name_second": "Bruno Miguel Silva Jorge"
	}
]