[
	{
		"id": 155057,
		"name": "Edward Nketiah",
		"name_second": "Edward Nketiah"
	},
	{
		"id": 241265,
		"name": "James Lannin-Sweet",
		"name_second": "James Lannin-Sweet"
	},
	{
		"id": 244629,
		"name": "Ayden Heaven",
		"name_second": "Ayden Heaven"
	},
	{
		"id": 249070,
		"name": "Myles Lewis Skelly",
		"name_second": "Myles Lewis Skelly"
	},
	{
		"id": 102096,
		"name": "Leandro Trossard",
		"name_second": "Leandro Trossard"
	},
	{
		"id": 155054,
		"name": "Reiss Nelson",
		"name_second": "Reiss Nelson"
	},
	{
		"id": 147555,
		"name": "Kai Havertz",
		"name_second": "Kai Havertz"
	},
	{
		"id": 231154,
		"name": "Mauro Bandeira",
		"name_second": "Mauro Bandeira"
	},
	{
		"id": 229902,
		"name": "Ethan Nwaneri",
		"name_second": "Ethan Nwaneri"
	},
	{
		"id": 123667,
		"name": "Martin Odegaard",
		"name_second": "Martin Odegaard"
	},
	{
		"id": 131976,
		"name": "Gabriel Fernando de Jesus",
		"name_second": "Gabriel Fernando de Jesus"
	},
	{
		"id": 166752,
		"name": "Emile Smith Rowe",
		"name_second": "Emile Smith Rowe"
	},
	{
		"id": 168935,
		"name": "Gabriel Teodoro Martinelli Silva",
		"name_second": "Gabriel Teodoro Martinelli Silva"
	},
	{
		"id": 187377,
		"name": "Fabio Vieira",
		"name_second": "Fabio Vieira"
	},
	{
		"id": 142267,
		"name": "Jorge Luiz Frello Filho,Jorginho",
		"name_second": "Jorge Luiz Frello Filho,Jorginho"
	},
	{
		"id": 101477,
		"name": "Mohamed El-Nenny",
		"name_second": "Mohamed El-Nenny"
	},
	{
		"id": 167450,
		"name": "William Saliba",
		"name_second": "William Saliba"
	},
	{
		"id": 234228,
		"name": "Reuell Walters",
		"name_second": "Reuell Walters"
	},
	{
		"id": 145438,
		"name": "Benjamin William White",
		"name_second": "Benjamin William White"
	},
	{
		"id": 266980,
		"name": "Brayden Clarke",
		"name_second": "Brayden Clarke"
	},
	{
		"id": 124473,
		"name": "Thomas Partey",
		"name_second": "Thomas Partey"
	},
	{
		"id": 151417,
		"name": "Gabriel Dos Santos Magalhaes",
		"name_second": "Gabriel Dos Santos Magalhaes"
	},
	{
		"id": 171322,
		"name": "Bukayo Saka",
		"name_second": "Bukayo Saka"
	},
	{
		"id": 179405,
		"name": "Jurrien Timber",
		"name_second": "Jurrien Timber"
	},
	{
		"id": 174939,
		"name": "Jakub Kiwior",
		"name_second": "Jakub Kiwior"
	},
	{
		"id": 88615,
		"name": "Cedric Ricardo Alves Soares",
		"name_second": "Cedric Ricardo Alves Soares"
	},
	{
		"id": 134682,
		"name": "Takehiro Tomiyasu",
		"name_second": "Takehiro Tomiyasu"
	},
	{
		"id": 130132,
		"name": "Olexandr Zinchenko",
		"name_second": "Olexandr Zinchenko"
	},
	{
		"id": 150472,
		"name": "Declan Rice",
		"name_second": "Declan Rice"
	},
	{
		"id": 146953,
		"name": "Aaron Ramsdale",
		"name_second": "Aaron Ramsdale"
	},
	{
		"id": 119086,
		"name": "David Raya",
		"name_second": "David Raya"
	},
	{
		"id": 199536,
		"name": "Karl Hein",
		"name_second": "Karl Hein"
	}
]