[
	{
		"id": 69876,
		"name": "Luc Castaignos",
		"name_second": "Luc Castaignos"
	},
	{
		"id": 177786,
		"name": "Alexander Nollenberger",
		"name_second": "Alexander Nollenberger"
	},
	{
		"id": 241075,
		"name": "Emir Kuhinja",
		"name_second": "Emir Kuhinja"
	},
	{
		"id": 177779,
		"name": "Xavier Amaechi",
		"name_second": "Xavier Amaechi"
	},
	{
		"id": 202778,
		"name": "Luca Schuler",
		"name_second": "Luca Schuler"
	},
	{
		"id": 182453,
		"name": "Bryan Silva Teixeira",
		"name_second": "Bryan Silva Teixeira"
	},
	{
		"id": 121555,
		"name": "Connor Krempicki",
		"name_second": "Connor Krempicki"
	},
	{
		"id": 238506,
		"name": "Jonah Fabisch",
		"name_second": "Jonah Fabisch"
	},
	{
		"id": 218047,
		"name": "Jason Ceka",
		"name_second": "Jason Ceka"
	},
	{
		"id": 125858,
		"name": "Baris Atik",
		"name_second": "Baris Atik"
	},
	{
		"id": 145949,
		"name": "Amara Conde",
		"name_second": "Amara Conde"
	},
	{
		"id": 238507,
		"name": "Stefan Korsch",
		"name_second": "Stefan Korsch"
	},
	{
		"id": 97201,
		"name": "Tatsuya Ito",
		"name_second": "Tatsuya Ito"
	},
	{
		"id": 194535,
		"name": "Andi Hoti",
		"name_second": "Andi Hoti"
	},
	{
		"id": 207435,
		"name": "Eldin Dzogovic",
		"name_second": "Eldin Dzogovic"
	},
	{
		"id": 221214,
		"name": "Jamie Lawrence",
		"name_second": "Jamie Lawrence"
	},
	{
		"id": 227428,
		"name": "Daniel Elfadli",
		"name_second": "Daniel Elfadli"
	},
	{
		"id": 166560,
		"name": "Herbert Bockhorn",
		"name_second": "Herbert Bockhorn"
	},
	{
		"id": 145590,
		"name": "Mo El Hankouri",
		"name_second": "Mo El Hankouri"
	},
	{
		"id": 232318,
		"name": "Daniel Heber",
		"name_second": "Daniel Heber"
	},
	{
		"id": 179052,
		"name": "Jean Hugonet",
		"name_second": "Jean Hugonet"
	},
	{
		"id": 162935,
		"name": "Silas Gnaka",
		"name_second": "Silas Gnaka"
	},
	{
		"id": 87062,
		"name": "Tobias Muller",
		"name_second": "Tobias Muller"
	},
	{
		"id": 140330,
		"name": "Tarek Chahed",
		"name_second": "Tarek Chahed"
	},
	{
		"id": 138444,
		"name": "Leon Bell Bell",
		"name_second": "Leon Bell Bell"
	},
	{
		"id": 131741,
		"name": "Dominik Reimann",
		"name_second": "Dominik Reimann"
	},
	{
		"id": 227396,
		"name": "Noah Kruth",
		"name_second": "Noah Kruth"
	},
	{
		"id": 238685,
		"name": "Robert Kampa",
		"name_second": "Robert Kampa"
	},
	{
		"id": 124035,
		"name": "Julian Pollersbeck",
		"name_second": "Julian Pollersbeck"
	}
]