[
	{
		"id": 150929,
		"name": "Facundo Peraza",
		"name_second": "Facundo Peraza"
	},
	{
		"id": 256744,
		"name": "Mouhameth Diop",
		"name_second": "Mouhameth Diop"
	},
	{
		"id": 209851,
		"name": "Mohamed Khalfan Ali",
		"name_second": "Mohamed Khalfan Ali"
	},
	{
		"id": 245626,
		"name": "Alhassane Tamboura",
		"name_second": "Alhassane Tamboura"
	},
	{
		"id": 203882,
		"name": "Diogo Capitao",
		"name_second": "Diogo Capitao"
	},
	{
		"id": 158741,
		"name": "Fabricio Fernandez",
		"name_second": "Fabricio Fernandez"
	},
	{
		"id": 229338,
		"name": "Wesley Braga",
		"name_second": "Wesley Braga"
	},
	{
		"id": 270037,
		"name": "Damilare Salaudeen",
		"name_second": "Damilare Salaudeen"
	},
	{
		"id": 191860,
		"name": "Saymon De Barros Cabral",
		"name_second": "Saymon De Barros Cabral"
	},
	{
		"id": 254110,
		"name": "Gabrel Camargo",
		"name_second": "Gabrel Camargo"
	}
]