[
	{
		"id": 268713,
		"name": "Charlie Lennon",
		"name_second": "Charlie Lennon"
	},
	{
		"id": 142025,
		"name": "Riley Mcgree",
		"name_second": "Riley Mcgree"
	},
	{
		"id": 203787,
		"name": "Alex Gilbert",
		"name_second": "Alex Gilbert"
	},
	{
		"id": 179313,
		"name": "Samuel Silvera",
		"name_second": "Samuel Silvera"
	},
	{
		"id": 146313,
		"name": "Emmanuel Latte Lath",
		"name_second": "Emmanuel Latte Lath"
	},
	{
		"id": 202777,
		"name": "Matthew Hoppe",
		"name_second": "Matthew Hoppe"
	},
	{
		"id": 207108,
		"name": "Josh Coburn",
		"name_second": "Josh Coburn"
	},
	{
		"id": 168242,
		"name": "Marcus Forss",
		"name_second": "Marcus Forss"
	},
	{
		"id": 183934,
		"name": "Isaiah Jones",
		"name_second": "Isaiah Jones"
	},
	{
		"id": 248157,
		"name": "Finley Cartwright",
		"name_second": "Finley Cartwright"
	},
	{
		"id": 274056,
		"name": "Shea Connor",
		"name_second": "Shea Connor"
	},
	{
		"id": 131703,
		"name": "Daniel Barlaser",
		"name_second": "Daniel Barlaser"
	},
	{
		"id": 170743,
		"name": "Hayden Hackney",
		"name_second": "Hayden Hackney"
	},
	{
		"id": 30646,
		"name": "Jonathan Howson",
		"name_second": "Jonathan Howson"
	},
	{
		"id": 162017,
		"name": "Lewis OBrien",
		"name_second": "Lewis OBrien"
	},
	{
		"id": 170196,
		"name": "Finn Azaz",
		"name_second": "Finn Azaz"
	},
	{
		"id": 201832,
		"name": "Sam Greenwood",
		"name_second": "Sam Greenwood"
	},
	{
		"id": 241247,
		"name": "Law McCabe",
		"name_second": "Law McCabe"
	},
	{
		"id": 26897,
		"name": "James Wilson",
		"name_second": "James Wilson"
	},
	{
		"id": 16182,
		"name": "Ricky van den Bergh",
		"name_second": "Ricky van den Bergh"
	},
	{
		"id": 36689,
		"name": "Matthew Clarke",
		"name_second": "Matthew Clarke"
	},
	{
		"id": 134778,
		"name": "Dael Fry",
		"name_second": "Dael Fry"
	},
	{
		"id": 125832,
		"name": "Patrick McNair",
		"name_second": "Patrick McNair"
	},
	{
		"id": 119573,
		"name": "Darragh Lenihan",
		"name_second": "Darragh Lenihan"
	},
	{
		"id": 174361,
		"name": "Alex Bangura",
		"name_second": "Alex Bangura"
	},
	{
		"id": 168802,
		"name": "Lukas Ahlefeld Engel",
		"name_second": "Lukas Ahlefeld Engel"
	},
	{
		"id": 197286,
		"name": "Luke Thomas",
		"name_second": "Luke Thomas"
	},
	{
		"id": 115021,
		"name": "Thomas Smith",
		"name_second": "Thomas Smith"
	},
	{
		"id": 69947,
		"name": "Luke Ayling",
		"name_second": "Luke Ayling"
	},
	{
		"id": 162120,
		"name": "Anfernee Dijksteel",
		"name_second": "Anfernee Dijksteel"
	},
	{
		"id": 144076,
		"name": "Seny Timothy Dieng",
		"name_second": "Seny Timothy Dieng"
	},
	{
		"id": 145065,
		"name": "Tom Glover",
		"name_second": "Tom Glover"
	},
	{
		"id": 31451,
		"name": "Jamie Jones",
		"name_second": "Jamie Jones"
	}
]