[
	{
		"id": 266334,
		"name": "Rodolfo Castro",
		"name_second": "Rodolfo Castro"
	},
	{
		"id": 154088,
		"name": "Richard Ballard",
		"name_second": "Richard Ballard"
	},
	{
		"id": 154672,
		"name": "Ilija Ilic",
		"name_second": "Ilija Ilic"
	},
	{
		"id": 269842,
		"name": "Yesin van der Pluijm",
		"name_second": "Yesin van der Pluijm"
	},
	{
		"id": 281153,
		"name": "Kingsford Adjei",
		"name_second": "Kingsford Adjei"
	},
	{
		"id": 271635,
		"name": "Jordan Skelton",
		"name_second": "Jordan Skelton"
	},
	{
		"id": 267089,
		"name": "Jalen Crisler",
		"name_second": "Jalen Crisler"
	},
	{
		"id": 267113,
		"name": "James Thomas",
		"name_second": "James Thomas"
	},
	{
		"id": 280629,
		"name": "Stuart Ritchie",
		"name_second": "Stuart Ritchie"
	},
	{
		"id": 269810,
		"name": "Sean O\"Hearn",
		"name_second": "Sean O\"Hearn"
	},
	{
		"id": 157550,
		"name": "Charlie Machell",
		"name_second": "Charlie Machell"
	},
	{
		"id": 179580,
		"name": "Sean Lewis",
		"name_second": "Sean Lewis"
	}
]