[
	{
		"id": 92916,
		"name": "Andrei Cristianc Truta",
		"name_second": "Andrei Cristianc Truta"
	},
	{
		"id": 93826,
		"name": "Octavian Chihaia",
		"name_second": "Octavian Chihaia"
	},
	{
		"id": 92917,
		"name": "Leonard Dobre",
		"name_second": "Leonard Dobre"
	},
	{
		"id": 49294,
		"name": "Marius Nae",
		"name_second": "Marius Nae"
	},
	{
		"id": 92920,
		"name": "Nicola Vasile",
		"name_second": "Nicola Vasile"
	},
	{
		"id": 90796,
		"name": "Lucian Constantin Chetan",
		"name_second": "Lucian Constantin Chetan"
	},
	{
		"id": 92924,
		"name": "Codrut Cioranu",
		"name_second": "Codrut Cioranu"
	},
	{
		"id": 48970,
		"name": "Stelian Stancu",
		"name_second": "Stelian Stancu"
	},
	{
		"id": 93825,
		"name": "Liviu Nicolae Rusu",
		"name_second": "Liviu Nicolae Rusu"
	},
	{
		"id": 92927,
		"name": "Razvan Farmache",
		"name_second": "Razvan Farmache"
	},
	{
		"id": 92929,
		"name": "Andrei Sorin Popescu",
		"name_second": "Andrei Sorin Popescu"
	}
]