[
	{
		"id": 121027,
		"name": "Rogvi Jacobsen",
		"name_second": "Rogvi Jacobsen"
	},
	{
		"id": 121028,
		"name": "Hanus Eliasen",
		"name_second": "Hanus Eliasen"
	},
	{
		"id": 121029,
		"name": "Vincent Jacobsen",
		"name_second": "Vincent Jacobsen"
	},
	{
		"id": 121030,
		"name": "Andy Olsen",
		"name_second": "Andy Olsen"
	},
	{
		"id": 127911,
		"name": "Uros Stojanov",
		"name_second": "Uros Stojanov"
	},
	{
		"id": 226242,
		"name": "Johan Petersen",
		"name_second": "Johan Petersen"
	},
	{
		"id": 234892,
		"name": "Runar Johnsson",
		"name_second": "Runar Johnsson"
	},
	{
		"id": 192227,
		"name": "Elvio Gelmini",
		"name_second": "Elvio Gelmini"
	},
	{
		"id": 116703,
		"name": "Danjal a Lakjuni",
		"name_second": "Danjal a Lakjuni"
	},
	{
		"id": 223706,
		"name": "Jhon Mena",
		"name_second": "Jhon Mena"
	},
	{
		"id": 234881,
		"name": "Bjarti Hojbro",
		"name_second": "Bjarti Hojbro"
	},
	{
		"id": 131601,
		"name": "Ari Ellingsgaard",
		"name_second": "Ari Ellingsgaard"
	},
	{
		"id": 121032,
		"name": "Frank Poulsen",
		"name_second": "Frank Poulsen"
	},
	{
		"id": 234884,
		"name": "Markus a Lakjuni",
		"name_second": "Markus a Lakjuni"
	},
	{
		"id": 64710,
		"name": "Bogi Lokin",
		"name_second": "Bogi Lokin"
	},
	{
		"id": 234888,
		"name": "Jakup i Lambanum",
		"name_second": "Jakup i Lambanum"
	},
	{
		"id": 273910,
		"name": "Tonni Thomsen",
		"name_second": "Tonni Thomsen"
	},
	{
		"id": 272450,
		"name": "Kasper Sommerstedt",
		"name_second": "Kasper Sommerstedt"
	},
	{
		"id": 121034,
		"name": "Hogni Zachariassen",
		"name_second": "Hogni Zachariassen"
	},
	{
		"id": 226241,
		"name": "Gundur Petersen",
		"name_second": "Gundur Petersen"
	},
	{
		"id": 234897,
		"name": "Gonzalo Zarate",
		"name_second": "Gonzalo Zarate"
	},
	{
		"id": 107111,
		"name": "Karl Lokin",
		"name_second": "Karl Lokin"
	},
	{
		"id": 147218,
		"name": "Bogi Petersen",
		"name_second": "Bogi Petersen"
	},
	{
		"id": 234883,
		"name": "Pol Jakup Lundsbjerg",
		"name_second": "Pol Jakup Lundsbjerg"
	},
	{
		"id": 234885,
		"name": "Hans Jakup Lervig",
		"name_second": "Hans Jakup Lervig"
	},
	{
		"id": 130720,
		"name": "Aki Petersen",
		"name_second": "Aki Petersen"
	},
	{
		"id": 121036,
		"name": "Viggo Johannesen",
		"name_second": "Viggo Johannesen"
	},
	{
		"id": 234886,
		"name": "Hans Jacobsen",
		"name_second": "Hans Jacobsen"
	},
	{
		"id": 121035,
		"name": "Jan Ellingsgaard",
		"name_second": "Jan Ellingsgaard"
	},
	{
		"id": 234882,
		"name": "Tori Olsen",
		"name_second": "Tori Olsen"
	},
	{
		"id": 143163,
		"name": "Poul Mikkelsen",
		"name_second": "Poul Mikkelsen"
	},
	{
		"id": 234890,
		"name": "Johann Hojbro",
		"name_second": "Johann Hojbro"
	},
	{
		"id": 234891,
		"name": "Petur Lundsbjerg",
		"name_second": "Petur Lundsbjerg"
	},
	{
		"id": 234896,
		"name": "Elias Lervig",
		"name_second": "Elias Lervig"
	},
	{
		"id": 234879,
		"name": "Tori Tradara",
		"name_second": "Tori Tradara"
	},
	{
		"id": 234887,
		"name": "Jakup Olsen",
		"name_second": "Jakup Olsen"
	},
	{
		"id": 121042,
		"name": "Mortan Joensen",
		"name_second": "Mortan Joensen"
	},
	{
		"id": 234889,
		"name": "Liggjas Heoinsson",
		"name_second": "Liggjas Heoinsson"
	}
]