[
	{
		"id": 98902,
		"name": "Jose Antonio Torrealba Acevedo",
		"name_second": "Jose Antonio Torrealba Acevedo"
	},
	{
		"id": 95586,
		"name": "James Cabezas",
		"name_second": "James Cabezas"
	},
	{
		"id": 142966,
		"name": "Angel Nieves",
		"name_second": "Angel Nieves"
	},
	{
		"id": 71879,
		"name": "Franklin Emir Gonzalez Quintero",
		"name_second": "Franklin Emir Gonzalez Quintero"
	},
	{
		"id": 224109,
		"name": "Luis Annese",
		"name_second": "Luis Annese"
	},
	{
		"id": 143315,
		"name": "Jose Araujo",
		"name_second": "Jose Araujo"
	},
	{
		"id": 144873,
		"name": "Wildiyonh Vivas Trejo",
		"name_second": "Wildiyonh Vivas Trejo"
	},
	{
		"id": 91965,
		"name": "Gerardo Jose Mendoza",
		"name_second": "Gerardo Jose Mendoza"
	},
	{
		"id": 131905,
		"name": "Wilson Antonio Mena Asprilla",
		"name_second": "Wilson Antonio Mena Asprilla"
	},
	{
		"id": 113278,
		"name": "Luiyi Erazo",
		"name_second": "Luiyi Erazo"
	},
	{
		"id": 39687,
		"name": "Leandro Diaz Prado",
		"name_second": "Leandro Diaz Prado"
	}
]